Metadata-Version: 2.1
Name: numba-namespace-extension
Version: 0.1.0
Summary: Easily create compiled namespace Numba extensions.
Home-page: UNKNOWN
License: UNKNOWN
Platform: UNKNOWN
License-File: LICENSE
